ax/utils/__init__.py
ax/utils/ax_tree/__init__.py
ax/utils/ax_tree/_ax_tree.so
ax/utils/ax_tree/ax_tree.py
devapp/__init__.py
devapp/app.py
devapp/da.py
devapp/dev_mode.py
devapp/gevent_patched.py
devapp/layer.py
devapp/load.py
devapp/logo
devapp/max.py
devapp/run.py
devapp/t
devapp/app_token/__init__.py
devapp/app_token/create_tokens.py
devapp/app_token/read_tokens.py
devapp/app_token/verify_token
devapp/components/__init__.py
devapp/components/cloudfoundry.py
devapp/components/gitlab.py
devapp/components/gitlab_runner.py
devapp/lib/README.md
devapp/lib/__init__.py
devapp/lib/sh.py
devapp/operations/binenv.py
devapp/operations/resources.py
devapp/plugins/dev_devapp/logging_style.py
devapp/plugins/dev_devapp/repo_sym_links.py
devapp/plugins/dev_devapp/personal_development_sandbox/__init__.py
devapp/plugins/ops_devapp/container_build.py
devapp/plugins/ops_devapp/container_pull.py
devapp/plugins/ops_devapp/fs_build.py
devapp/plugins/ops_devapp/life_cycle.py
devapp/plugins/ops_devapp/log_view.py
devapp/plugins/ops_devapp/pkgs.py
devapp/plugins/ops_devapp/run.py
devapp/plugins/ops_devapp/arch/resource_install.py
devapp/plugins/ops_devapp/arch/resource_run.py
devapp/plugins/ops_devapp/arch/resources.py.dis
devapp/plugins/ops_devapp/arch/resources_list.py
devapp/plugins/ops_devapp/arch/wait_for_port.py
devapp/plugins/ops_devapp/infra_aws_cloud/__init__.py
devapp/plugins/ops_devapp/infra_digital_ocean/__init__.py
devapp/plugins/ops_devapp/infra_hetzner_cloud/__init__.py
devapp/plugins/ops_devapp/kubectl/__init__.py
devapp/plugins/ops_devapp/project/__init__.py
devapp/plugins/ops_devapp/project/devinstall/__init__.py
devapp/plugins/ops_devapp/system/__init__.py
devapp/plugins/ops_devapp/system/tools.py
devapp/plugins/ops_devapp/system/templates/inst_base.sh
devapp/spec/build.py
devapp/spec/find_paths_in_fs_components.py
devapp/spec/fs_components.py
devapp/spec/links.py
devapp/spec/os_tools.py
devapp/spec/templ.py
devapp/spec/tools.py
devapp/spec/templates/unit
devapps-2025.9.20.dist-info/METADATA
devapps-2025.9.20.dist-info/WHEEL
devapps-2025.9.20.dist-info/entry_points.txt
devapps-2025.9.20.dist-info/licenses/LICENSE
devapps-2025.9.20.dist-info/RECORD
