Metadata-Version: 2.4
Name: devapps
Version: 2025.9.20
Summary: Apps - End to End.
Project-URL: Homepage, https://axgkl.github.io/devapps
Project-URL: Repository, https://github.com/AXGKl/devapps
Project-URL: packagehome, https://pypi.com/
Project-URL: discusshome, https://join.skype.com/
Author-email: Gunther Klessinger <g_kle_ss_ing_er@gmx.de>
License: BSD
License-File: LICENSE
Classifier: Programming Language :: Python :: 3
Classifier: Programming Language :: Python :: 3.9
Classifier: Programming Language :: Python :: 3.10
Classifier: Programming Language :: Python :: 3.11
Classifier: Programming Language :: Python :: 3.12
Classifier: Programming Language :: Python :: 3.13
Requires-Python: <4.0,>=3.9
Requires-Dist: absl-py
Requires-Dist: inflection
Requires-Dist: jsondiff
Requires-Dist: pycond
Requires-Dist: requests
Requires-Dist: rich
Requires-Dist: structlog>=24.1.0
Requires-Dist: toml
